{
  "title": "Fumetsu no Anata e Season 3 Subtitle Indonesia",
  "slug": "fumetsu-no-anata-e-season-3-subtitle-indonesia",
  "url": "https://x3.sokuja.uk/anime/fumetsu-no-anata-e-season-3-subtitle-indonesia/",
  "poster": "https://gbr.sokuja.uk/wp-content/uploads/2025/09/Fumetsu_no_Anata_e_Season_3_.jpg",
  "synopsis": "To Your Eternity adalah kisah epik tentang Fushi, makhluk abadi yang dilempar ke Bumi tanpa identitas, perasaan, atau tujuan. Fushi belajar menjadi manusia melalui pengalaman kehilangan, cinta, dan perjuangan—dimulai dari menjadi batu, serigala kutub, hingga seorang bocah manusia bernama FushiMusim ketiga, yang dijadwalkan tayang 4 Oktober 2025, akan mengeksplorasi Modern Day Arc—menghadirkan Fushi di era modern penuh teknologi, konflik moral, dan tantangan baruFushi kini berhadapan dengan dunia yang telah berubah drastis: kota, kendaraan, manusia modern, bahkan godaan kebersamaan. Namun, ancaman tak kunjung hilang—Nokkers telah berkembang, menyusup ke dalam jiwa manusia, mengaburkan batas antara hidup dan hantu. Fushi harus memutuskan apakah akan membasmi mereka atau berdamai, sambil menghadapi kebenaran tentang penciptanya, The BeholderKata Kunci : Fantasy, Drama, Epik \u0026 Emosional, Fantasi Modern (Modern Day Arc), Supernatural \u0026 Psychological, Pencarian Identitas, Pertumbuhan Karakter Abadi, Moral Ambiguity, Nokkers Menyatu dengan Manusia, Konfrontasi dengan Pencipta, Perubahan Zaman \u0026 TeknologiSeries Sebelumnya : Fumetsu no Anata e Season 2 Subtitle Indonesia",
  "episodes": [
    {
      "episode": 1,
      "title": "Fumetsu no Anata e S3 Episode 1 Subtitle Indonesia",
      "url_page": "https://x3.sokuja.uk/fumetsu-no-anata-e-s3-episode-1-subtitle-indonesia/",
      "streams": {
        "1080p": "https://storages.sokuja.id/2025-fall/fumetsu-s3/SOKUJA.NET-FNAE-1.1080p.mp4",
        "480p": "https://storages.sokuja.id/2025-fall/fumetsu-s3/SOKUJA.NET-FNAE-1.480p.mp4",
        "720p": "https://storages.sokuja.id/2025-fall/fumetsu-s3/SOKUJA.NET-FNAE-1.720p.mp4"
      }
    },
    {
      "episode": 2,
      "title": "Fumetsu no Anata e S3 Episode 2 Subtitle Indonesia",
      "url_page": "https://x3.sokuja.uk/fumetsu-no-anata-e-s3-episode-2-subtitle-indonesia/",
      "streams": {
        "1080p": "https://storages.sokuja.id/2025-fall/fumetsu-s3/SOKUJA.NET-FNAE-2.1080p.mp4",
        "480p": "https://storages.sokuja.id/2025-fall/fumetsu-s3/SOKUJA.NET-FNAE-2.480p.mp4",
        "720p": "https://storages.sokuja.id/2025-fall/fumetsu-s3/SOKUJA.NET-FNAE-2.720p.mp4"
      }
    },
    {
      "episode": 3,
      "title": "Fumetsu no Anata e S3 Episode 3 Subtitle Indonesia",
      "url_page": "https://x3.sokuja.uk/fumetsu-no-anata-e-s3-episode-3-subtitle-indonesia/",
      "streams": {
        "1080p": "https://storages.sokuja.id/2025-fall/fumetsu-s3/SOKUJA.NET-FNAE-3.1080p.mp4",
        "480p": "https://storages.sokuja.id/2025-fall/fumetsu-s3/SOKUJA.NET-FNAE-3.480p.mp4",
        "720p": "https://storages.sokuja.id/2025-fall/fumetsu-s3/SOKUJA.NET-FNAE-3.720p.mp4"
      }
    },
    {
      "episode": 4,
      "title": "Fumetsu no Anata e S3 Episode 4 Subtitle Indonesia",
      "url_page": "https://x3.sokuja.uk/fumetsu-no-anata-e-s3-episode-4-subtitle-indonesia/",
      "streams": {
        "1080p": "https://storages.sokuja.id/2025-fall/fumetsu-s3/SOKUJA.NET-FNAE-4.1080p.mp4",
        "480p": "https://storages.sokuja.id/2025-fall/fumetsu-s3/SOKUJA.NET-FNAE-4.480p.mp4",
        "720p": "https://storages.sokuja.id/2025-fall/fumetsu-s3/SOKUJA.NET-FNAE-4.720p.mp4"
      }
    },
    {
      "episode": 5,
      "title": "Fumetsu no Anata e S3 Episode 5 Subtitle Indonesia",
      "url_page": "https://x3.sokuja.uk/fumetsu-no-anata-e-s3-episode-5-subtitle-indonesia/",
      "streams": {
        "1080p": "https://storages.sokuja.id/2025-fall/fumetsu-s3/SOKUJA.NET-FNAE-5.1080p.mp4",
        "480p": "https://storages.sokuja.id/2025-fall/fumetsu-s3/SOKUJA.NET-FNAE-5.480p.mp4",
        "720p": "https://storages.sokuja.id/2025-fall/fumetsu-s3/SOKUJA.NET-FNAE-5.720p.mp4"
      }
    },
    {
      "episode": 6,
      "title": "Fumetsu no Anata e S3 Episode 6 Subtitle Indonesia",
      "url_page": "https://x3.sokuja.uk/fumetsu-no-anata-e-s3-episode-6-subtitle-indonesia/",
      "streams": {
        "1080p": "https://storages.sokuja.id/2025-fall/fumetsu-s3/SOKUJA.NET-FNAE-6.1080p.mp4",
        "480p": "https://storages.sokuja.id/2025-fall/fumetsu-s3/SOKUJA.NET-FNAE-6.480p.mp4",
        "720p": "https://storages.sokuja.id/2025-fall/fumetsu-s3/SOKUJA.NET-FNAE-6.720p.mp4"
      }
    },
    {
      "episode": 7,
      "title": "Fumetsu no Anata e S3 Episode 7 Subtitle Indonesia",
      "url_page": "https://x3.sokuja.uk/fumetsu-no-anata-e-s3-episode-7-subtitle-indonesia/",
      "streams": {
        "1080p": "https://storages.sokuja.id/2025-fall/fumetsu-s3/SOKUJA.NET-FNAE-7.1080p.mp4",
        "480p": "https://storages.sokuja.id/2025-fall/fumetsu-s3/SOKUJA.NET-FNAE-7.480p.mp4",
        "720p": "https://storages.sokuja.id/2025-fall/fumetsu-s3/SOKUJA.NET-FNAE-7.720p.mp4"
      }
    },
    {
      "episode": 8,
      "title": "Fumetsu no Anata e S3 Episode 8 Subtitle Indonesia",
      "url_page": "https://x3.sokuja.uk/fumetsu-no-anata-e-s3-episode-8-subtitle-indonesia/",
      "streams": {
        "1080p": "https://storages.sokuja.id/2025-fall/fumetsu-s3/SOKUJA.NET-FNAE-8.1080p.mp4",
        "480p": "https://storages.sokuja.id/2025-fall/fumetsu-s3/SOKUJA.NET-FNAE-8.480p.mp4",
        "720p": "https://storages.sokuja.id/2025-fall/fumetsu-s3/SOKUJA.NET-FNAE-8.720p.mp4"
      }
    },
    {
      "episode": 9,
      "title": "Fumetsu no Anata e S3 Episode 9 Subtitle Indonesia",
      "url_page": "https://x3.sokuja.uk/fumetsu-no-anata-e-s3-episode-9-subtitle-indonesia/",
      "streams": {
        "1080p": "https://storages.sokuja.id/2025-fall/fumetsu-s3/SOKUJA.NET-FNAE-9.1080p.mp4",
        "480p": "https://storages.sokuja.id/2025-fall/fumetsu-s3/SOKUJA.NET-FNAE-9.480p.mp4",
        "720p": "https://storages.sokuja.id/2025-fall/fumetsu-s3/SOKUJA.NET-FNAE-9.720p.mp4"
      }
    },
    {
      "episode": 10,
      "title": "Fumetsu no Anata e S3 Episode 10 Subtitle Indonesia",
      "url_page": "https://x3.sokuja.uk/fumetsu-no-anata-e-s3-episode-10-subtitle-indonesia/",
      "streams": {
        "1080p": "https://storages.sokuja.id/2025-fall/fumetsu-s3/SOKUJA.NET-FNAE-10.1080p.mp4",
        "480p": "https://storages.sokuja.id/2025-fall/fumetsu-s3/SOKUJA.NET-FNAE-10.480p.mp4",
        "720p": "https://storages.sokuja.id/2025-fall/fumetsu-s3/SOKUJA.NET-FNAE-10.720p.mp4"
      }
    },
    {
      "episode": 11,
      "title": "Fumetsu no Anata e S3 Episode 11 Subtitle Indonesia",
      "url_page": "https://x3.sokuja.uk/fumetsu-no-anata-e-s3-episode-11-subtitle-indonesia/",
      "streams": {
        "1080p": "https://storages.sokuja.id/2025-fall/fumetsu-s3/SOKUJA.NET-FNAE-11.1080p.mp4",
        "480p": "https://storages.sokuja.id/2025-fall/fumetsu-s3/SOKUJA.NET-FNAE-11.480p.mp4",
        "720p": "https://storages.sokuja.id/2025-fall/fumetsu-s3/SOKUJA.NET-FNAE-11.720p.mp4"
      }
    },
    {
      "episode": 12,
      "title": "Fumetsu no Anata e S3 Episode 12 Subtitle Indonesia",
      "url_page": "https://x3.sokuja.uk/fumetsu-no-anata-e-s3-episode-12-subtitle-indonesia/",
      "streams": {
        "1080p": "https://storages.sokuja.id/2025-fall/fumetsu-s3/SOKUJA.NET-FNAE-12.1080p-qeknq.mp4",
        "480p": "https://storages.sokuja.id/2025-fall/fumetsu-s3/SOKUJA.NET-FNAE-12.480p-eqjfnk.mp4",
        "720p": "https://storages.sokuja.id/2025-fall/fumetsu-s3/SOKUJA.NET-FNAE-12.720p-qjbjkq.mp4"
      }
    },
    {
      "episode": 13,
      "title": "Fumetsu no Anata e S3 Episode 13 Subtitle Indonesia",
      "url_page": "https://x3.sokuja.uk/fumetsu-no-anata-e-s3-episode-13-subtitle-indonesia/",
      "streams": {
        "1080p": "https://storages.sokuja.id/2025-fall/fumetsu-s3/SOKUJA.NET-FNAE-13.1080p-ajfninka.mp4",
        "480p": "https://storages.sokuja.id/2025-fall/fumetsu-s3/SOKUJA.NET-FNAE-13.480p-qonmzja.mp4",
        "720p": "https://storages.sokuja.id/2025-fall/fumetsu-s3/SOKUJA.NET-FNAE-13.720p-awmfnozn.mp4"
      }
    },
    {
      "episode": 14,
      "title": "Fumetsu no Anata e S3 Episode 14 Subtitle Indonesia",
      "url_page": "https://x3.sokuja.uk/fumetsu-no-anata-e-s3-episode-14-subtitle-indonesia/",
      "streams": {
        "1080p": "https://storages.sokuja.id/2026-winter/fumetsu-s3/SOKUJA.NET-FNAE-14.1080p-eqjbkjvmz.mp4",
        "480p": "https://storages.sokuja.id/2026-winter/fumetsu-s3/SOKUJA.NET-FNAE-14.480p-vjknqkjnv.mp4",
        "720p": "https://storages.sokuja.id/2026-winter/fumetsu-s3/SOKUJA.NET-FNAE-14.720p-advnkjvn.mp4"
      }
    },
    {
      "episode": 15,
      "title": "Fumetsu no Anata e S3 Episode 15 Subtitle Indonesia",
      "url_page": "https://x3.sokuja.uk/fumetsu-no-anata-e-s3-episode-15-subtitle-indonesia/",
      "streams": {
        "1080p": "https://storages.sokuja.id/2026-winter/fumetsu-s3/SOKUJA.NET-FNAE-15.1080p-qegjlqhgls.mp4",
        "480p": "https://storages.sokuja.id/2026-winter/fumetsu-s3/SOKUJA.NET-FNAE-15.480p-qeglkhqgl.mp4",
        "720p": "https://storages.sokuja.id/2026-winter/fumetsu-s3/SOKUJA.NET-FNAE-15.720p-qgfjqngeg.mp4"
      }
    },
    {
      "episode": 16,
      "title": "Fumetsu no Anata e S3 Episode 16 Subtitle Indonesia",
      "url_page": "https://x3.sokuja.uk/fumetsu-no-anata-e-s3-episode-16-subtitle-indonesia/",
      "streams": {
        "1080p": "https://storages.sokuja.id/2026-winter/fumetsu-s3/SOKUJA.NET-FNAE-16.1080p-qefjnkjq.mp4",
        "480p": "https://storages.sokuja.id/2026-winter/fumetsu-s3/SOKUJA.NET-FNAE-16.480p-qegkjqnjkg.mp4",
        "720p": "https://storages.sokuja.id/2026-winter/fumetsu-s3/SOKUJA.NET-FNAE-16.720p-qegkjkj.mp4"
      }
    }
  ]
}
