{
  "title": "Yuusha ga Shinda! Subtitle Indonesia",
  "slug": "yuusha-ga-shinda-subtitle-indonesia",
  "url": "https://x3.sokuja.uk/anime/yuusha-ga-shinda-subtitle-indonesia/",
  "poster": "https://gbr.sokuja.uk/wp-content/uploads/2023/03/yusha.ga_.shinda....jpg",
  "synopsis": "Jauh di utara dunia terletak Gerbang Neraka, sebuah portal yang sebelumnya digunakan oleh Raja Iblis untuk menyerang dunia manusia. Berkat pahlawan legendaris Shion Bladearts, pengguna Excalibur, dan teman-temannya yang setia, Gerbang itu ditutup dan ancaman iblis ditaklukkan.Sayangnya, segel itu tidak lengkap dan mulai melemah, memungkinkan iblis untuk sekali lagi memulai serangan mereka. Khawatir tentang keamanan desanya, petani yang egois dan mesum, Touka Scott, menggali jebakan untuk bertahan melawan iblis. Tapi jangan takut, karena Shion sedang dalam perjalanan untuk menyegel Gerbang Neraka dan menyelamatkan umat manusia!Atau setidaknya begitu, karena pahlawan legendaris itu mati, jatuh ke salah satu jebakan yang digali Touka. Untungnya, berurusan dengan orang mati adalah keahlian ahli nujum Anri Haynesworth. Meskipun dia tidak dapat menghidupkannya kembali, Anri setidaknya dapat menyelamatkan pencarian mereka dengan memaksa jiwa Touka ke dalam tubuh Shion yang membusuk dan menyeretnya ke Gerbang Neraka menggantikan Shion. Tak mau ketinggalan, teman masa kecil Touka, Yuna Yunis, ikut serta. Bersama-sama, mereka bertiga berangkat sebagai pihak yang mungkin paling tidak cocok untuk mencoba menyelamatkan dunia!",
  "episodes": [
    {
      "episode": 1,
      "title": "Yuusha ga Shinda Episode 1 Subtitle Indonesia",
      "url_page": "https://x3.sokuja.uk/yuusha-ga-shinda-episode-1-subtitle-indonesia/",
      "streams": {
        "480p": "https://global.nontony.uk/video2/yuusha.ga.shinda/sokuja.net-YGS.1-480p.mp4",
        "720p": "https://global.nontony.uk/video2/yuusha.ga.shinda/sokuja.net-YGS.1-720p.mp4"
      }
    },
    {
      "episode": 2,
      "title": "Yuusha ga Shinda Episode 2 Subtitle Indonesia",
      "url_page": "https://x3.sokuja.uk/yuusha-ga-shinda-episode-2-subtitle-indonesia/",
      "streams": {
        "480p": "https://global.nontony.uk/video2/yuusha.ga.shinda/sokuja.net-YGS.2.v2-480p.mp4",
        "720p": "https://global.nontony.uk/video2/yuusha.ga.shinda/sokuja.net-YGS.2.v2-720p.mp4"
      }
    },
    {
      "episode": 3,
      "title": "Yuusha ga Shinda Episode 3 Subtitle Indonesia",
      "url_page": "https://x3.sokuja.uk/yuusha-ga-shinda-episode-3-subtitle-indonesia/",
      "streams": {
        "480p": "https://global.nontony.uk/video2/yuusha.ga.shinda/sokuja.net-YGS.3-480p.mp4",
        "720p": "https://global.nontony.uk/video2/yuusha.ga.shinda/sokuja.net-YGS.3-720p.mp4"
      }
    },
    {
      "episode": 4,
      "title": "Yuusha ga Shinda Episode 4 Subtitle Indonesia",
      "url_page": "https://x3.sokuja.uk/yuusha-ga-shinda-episode-4-subtitle-indonesia/",
      "streams": {
        "480p": "https://global.nontony.uk/video2/yuusha.ga.shinda/sokuja.net-YGS.4-480p.mp4",
        "720p": "https://global.nontony.uk/video2/yuusha.ga.shinda/sokuja.net-YGS.4-720p.mp4"
      }
    },
    {
      "episode": 5,
      "title": "Yuusha ga Shinda Episode 5 Subtitle Indonesia",
      "url_page": "https://x3.sokuja.uk/yuusha-ga-shinda-episode-5-subtitle-indonesia/",
      "streams": {
        "480p": "https://global.nontony.uk/video2/yuusha.ga.shinda/sokuja.net-YGS.5-480p.mp4",
        "720p": "https://global.nontony.uk/video2/yuusha.ga.shinda/sokuja.net-YGS.5-720p.mp4"
      }
    },
    {
      "episode": 6,
      "title": "Yuusha ga Shinda Episode 6 Subtitle Indonesia",
      "url_page": "https://x3.sokuja.uk/yuusha-ga-shinda-episode-6-subtitle-indonesia/",
      "streams": {
        "720p": "https://global.nontony.uk/video2/yuusha.ga.shinda/sokuja.net-YGS.6-720p.mp4"
      }
    },
    {
      "episode": 7,
      "title": "Yuusha ga Shinda Episode 7 Subtitle Indonesia",
      "url_page": "https://x3.sokuja.uk/yuusha-ga-shinda-episode-7-subtitle-indonesia/",
      "streams": {
        "720p": "https://global.nontony.uk/video2/yuusha.ga.shinda/sokuja.net-YGS.7-720p.mp4"
      }
    },
    {
      "episode": 8,
      "title": "Yuusha ga Shinda Episode 8 Subtitle Indonesia",
      "url_page": "https://x3.sokuja.uk/yuusha-ga-shinda-episode-8-subtitle-indonesia/",
      "streams": {
        "720p": "https://global.nontony.uk/video2/yuusha.ga.shinda/sokuja.net-YGS.8-720p.mp4"
      }
    },
    {
      "episode": 9,
      "title": "Yuusha ga Shinda Episode 9 Subtitle Indonesia",
      "url_page": "https://x3.sokuja.uk/yuusha-ga-shinda-episode-9-subtitle-indonesia/",
      "streams": {
        "720p": "https://global.nontony.uk/video2/yuusha.ga.shinda/sokuja.net-YGS.9-720p.mp4"
      }
    },
    {
      "episode": 10,
      "title": "Yuusha ga Shinda Episode 10 Subtitle Indonesia",
      "url_page": "https://x3.sokuja.uk/yuusha-ga-shinda-episode-10-subtitle-indonesia/",
      "streams": {
        "720p": "https://global.nontony.uk/video2/yuusha.ga.shinda/sokuja.net-ygs.10-720p.mp4"
      }
    },
    {
      "episode": 11,
      "title": "Yuusha ga Shinda Episode 11 Subtitle Indonesia",
      "url_page": "https://x3.sokuja.uk/yuusha-ga-shinda-episode-11-subtitle-indonesia/",
      "streams": {
        "480p": "https://global.nontony.uk/video2/yuusha.ga.shinda/sokuja.net-YGS.11-480p.mp4",
        "720p": "https://global.nontony.uk/video2/yuusha.ga.shinda/sokuja.net-YGS.11-720p.mp4"
      }
    },
    {
      "episode": 12,
      "title": "(END) Yuusha ga Shinda Episode 12 Subtitle Indonesia",
      "url_page": "https://x3.sokuja.uk/end-yuusha-ga-shinda-episode-12-subtitle-indonesia/",
      "streams": {
        "480p": "https://global.nontony.uk/video2/yuusha.ga.shinda/sokuja.net-YGS.12-480p.mp4",
        "720p": "https://global.nontony.uk/video2/yuusha.ga.shinda/sokuja.net-YGS.12-720p.mp4"
      }
    }
  ]
}
